a2y_paratree.cp312-win_amd64.pyd
a2y_paratree-1.1.2.dist-info/LICENSE
a2y_paratree-1.1.2.dist-info/METADATA
a2y_paratree-1.1.2.dist-info/WHEEL
a2y_paratree-1.1.2.dist-info/top_level.txt
a2y_paratree-1.1.2.dist-info/RECORD
